rw_api_tools/__init__.py
rw_api_tools/rw_api_tools.py
rw_api_tools-1.0.7.dist-info/DESCRIPTION.rst
rw_api_tools-1.0.7.dist-info/METADATA
rw_api_tools-1.0.7.dist-info/RECORD
rw_api_tools-1.0.7.dist-info/WHEEL
rw_api_tools-1.0.7.dist-info/metadata.json
rw_api_tools-1.0.7.dist-info/top_level.txt
